multinosetests/__init__.py
multinosetests/multinosetests.py
multinosetests-0.2.2.dist-info/DESCRIPTION.rst
multinosetests-0.2.2.dist-info/METADATA
multinosetests-0.2.2.dist-info/RECORD
multinosetests-0.2.2.dist-info/WHEEL
multinosetests-0.2.2.dist-info/entry_points.txt
multinosetests-0.2.2.dist-info/metadata.json
multinosetests-0.2.2.dist-info/top_level.txt
