Metadata-Version: 1.1
Name: multinosetests
Version: 0.2.2
Summary: Helper utility to run multiple nosetests suites. Useful for makefile scripts.
Home-page: https://github.com/Dealertrack/multinosetests
Author: Miroslav Shubernetskiy
Author-email: UNKNOWN
License: UNKNOWN
Keywords: test nosetests nose nosetest
Platform: UNKNOWN
Classifier: License :: OSI Approved :: MIT License
Classifier: Programming Language :: Python
Classifier: Programming Language :: Python :: 3
Classifier: Development Status :: 4 - Beta
Classifier: Intended Audience :: Developers
Classifier: Topic :: Software Development :: Libraries :: Python Modules
Classifier: Topic :: Software Development :: Testing
